gfftools/__init__.py
gfftools/attributes.py
gfftools/helper.py
gfftools/io.py
gfftools/model.py
gfftools-0.0.4.dist-info/LICENSE
gfftools-0.0.4.dist-info/METADATA
gfftools-0.0.4.dist-info/WHEEL
gfftools-0.0.4.dist-info/top_level.txt
gfftools-0.0.4.dist-info/RECORD
