Metadata-Version: 2.1
Name: gfftools
Version: 0.0.4
Summary: Parse GFF files.
Home-page: https://github.com/kaiserpreusse/gfftools
Author: Martin Preusse
Author-email: martin.preusse@gmail.com
License: MIT
Keywords: GFF,Genomics
Platform: UNKNOWN
Classifier: Programming Language :: Python
Classifier: Intended Audience :: Developers
License-File: LICENSE
